Facextractor-1.0.2.data/scripts/facextractor
facextractor/Friends.py
facextractor/Messages.py
facextractor/__base__.py
facextractor/__init__.py
Facextractor-1.0.2.dist-info/LICENSE
Facextractor-1.0.2.dist-info/METADATA
Facextractor-1.0.2.dist-info/WHEEL
Facextractor-1.0.2.dist-info/top_level.txt
Facextractor-1.0.2.dist-info/RECORD
