Metadata-Version: 2.1
Name: Facextractor
Version: 1.0.2
Summary: Facebook Data Extractor, simple tool for read and analyze facebook dump (JSON format)
Home-page: https://github.com/geekmoss/facextractor
Author: Jakub Janeček
Author-email: jakub.janecek@fw-fw.cz
License: MIT
Platform: UNKNOWN
Classifier: Programming Language :: Python :: 3.6
Classifier: Programming Language :: Python :: 3.7
Classifier: License :: OSI Approved :: MIT License
Classifier: Operating System :: OS Independent
Requires-Dist: Click
